{
  "agent": "xiaozhengge",
  "display": "🔧 小政哥",
  "task": "校验器 + 环境 + L10~L11 高级课",
  "status": "done",
  "started_ms": 1783816768661,
  "ended_ms": 1783818332311,
  "progress_pct": 100,
  "steps": [
    "编写 check.py 质量门禁（零依赖，退出码 0/1）",
    "编写 setup-env.md（虚拟机/WSL2/云主机/容器）",
    "撰写 L10 四课（sudo/sshsec/firewall/audit）",
    "撰写 L11 五课（cpu/mem/io/net/bench）",
    "编写 steps.js（6 步，id 1001~，仅 l10-sudo/l11-cpu 开沙盒）"
  ],
  "current_step": "全部完成",
  "deliverables": [
    "tools/check.py",
    "docs/setup-env.md",
    "content/l10-sudo.md ~ l11-bench.md（9 课）",
    "partner-workspace/xiaozhengge/steps.js"
  ]
}
